.gitignore
.readthedocs.yml
CHANGES.rst
MANIFEST.in
README.rst
pyproject.toml
setup.cfg
setup.py
tox.ini
.github/workflows/ci_cron_weekly.yml
.github/workflows/ci_tests.yml
docs/Makefile
docs/conf.py
docs/index.rst
docs/make.bat
docs/pycause/index.rst
licenses/LICENSE.rst
licenses/README.rst
pycause/__init__.py
pycause/_astropy_init.py
pycause/conftest.py
pycause/example_mod.py
pycause/version.py
pycause.egg-info/PKG-INFO
pycause.egg-info/SOURCES.txt
pycause.egg-info/dependency_links.txt
pycause.egg-info/entry_points.txt
pycause.egg-info/not-zip-safe
pycause.egg-info/requires.txt
pycause.egg-info/top_level.txt
pycause/example_subpkg/__init__.py
pycause/example_subpkg/setup_package.py
pycause/example_subpkg/data/.gitignore
pycause/example_subpkg/tests/__init__.py
pycause/tests/__init__.py
pycause/tests/test_example.py
pycause/utils/__init__.py
pycause/utils/tests/__init__.py