Metadata-Version: 2.1
Name: pycause
Version: 0.0.1
Summary: rendering emergent causal structure
Home-page: https://github.com/sibirrer/pycause
Author: Simon Birrer
Author-email: sibirrer@gmail.com
License: BSD 3-Clause
Platform: UNKNOWN
Requires-Python: >=3.6
Provides-Extra: test
Provides-Extra: docs
